mollia_bullet/__init__.py
mollia_bullet/core.cpython-38-i386-linux-gnu.so
mollia_bullet-1.0.1.dist-info/RECORD
mollia_bullet-1.0.1.dist-info/LICENSE
mollia_bullet-1.0.1.dist-info/METADATA
mollia_bullet-1.0.1.dist-info/top_level.txt
mollia_bullet-1.0.1.dist-info/WHEEL
