Metadata-Version: 2.1
Name: mollia-bullet
Version: 1.0.1
Summary: UNKNOWN
Home-page: UNKNOWN
Author: Mollia Zrt.
License: MIT
Platform: UNKNOWN
License-File: LICENSE
Requires-Dist: numpy
